ocrd_olahd_client/__init__.py
ocrd_olahd_client/cli.py
ocrd_olahd_client/client.py
ocrd_olahd_client/ocrd-tool.json
ocrd_olahd_client/processor.py
ocrd_olahd_client-0.0.2.dist-info/LICENSE
ocrd_olahd_client-0.0.2.dist-info/METADATA
ocrd_olahd_client-0.0.2.dist-info/WHEEL
ocrd_olahd_client-0.0.2.dist-info/entry_points.txt
ocrd_olahd_client-0.0.2.dist-info/top_level.txt
ocrd_olahd_client-0.0.2.dist-info/RECORD
