Metadata-Version: 2.1
Name: ocrd-olahd-client
Version: 0.0.2
Summary: OCR-D processor and client for OLA-HD
Home-page: https://github.com/OCR-D/ocrd_olahd_client
Author: Konstantin Baierer
Author-email: unixprog@gmail.com
License: Apache 2.0
License-File: LICENSE
Requires-Dist: ocrd (>=2.16.1)
Requires-Dist: requests (>=2.24.0)
Requires-Dist: setuptools (>=50)
Requires-Dist: requests-toolbelt (>=0.9.1)
